firebird/lib/__about__.py
firebird/lib/__init__.py
firebird/lib/gstat.py
firebird/lib/log.py
firebird/lib/logmsgs.py
firebird/lib/monitor.py
firebird/lib/schema.py
firebird/lib/trace.py
firebird_lib-2.0.0.dist-info/METADATA
firebird_lib-2.0.0.dist-info/WHEEL
firebird_lib-2.0.0.dist-info/licenses/LICENSE
firebird_lib-2.0.0.dist-info/RECORD
