Metadata-Version: 2.4
Name: firebird-lib
Version: 2.0.0
Summary: Firebird driver extension library
Project-URL: Home, https://github.com/FirebirdSQL/python3-lib
Project-URL: Documentation, https://firebird-lib.rtfd.io
Project-URL: Issues, https://github.com/FirebirdSQL/python3-lib/issues
Project-URL: Funding, https://github.com/sponsors/pcisar
Project-URL: Source, https://github.com/FirebirdSQL/python3-lib
Author-email: Pavel Cisar <pcisar@users.sourceforge.net>
License: MIT License
License-File: LICENSE
Keywords: Firebird,RDBMS,driver,extension,library
Classifier: Development Status :: 5 - Production/Stable
Classifier: Intended Audience :: Developers
Classifier: License :: OSI Approved :: MIT License
Classifier: Operating System :: MacOS
Classifier: Operating System :: Microsoft :: Windows
Classifier: Operating System :: POSIX :: Linux
Classifier: Programming Language :: Python :: 3 :: Only
Classifier: Programming Language :: Python :: 3.11
Classifier: Programming Language :: Python :: 3.12
Classifier: Programming Language :: Python :: 3.13
Classifier: Topic :: Database
Classifier: Topic :: Software Development
Requires-Python: >=3.11
Requires-Dist: firebird-base~=2.0
Requires-Dist: firebird-driver~=2.0
